packaging_demo/__init__.py
packaging_demo/my_file.py
packaging_demo/my_other_file.py
packaging_demo/test.json
packaging_demo/my_folder/__init__.py
packaging_demo/my_folder/my_nested_file.py
packaging_demo/my_folder/sub_package/__init__.py
packaging_demo/my_folder/sub_package/some_deeply_nested_file.py
packaging_demo_py_to_prd_test-0.5.0.dist-info/METADATA
packaging_demo_py_to_prd_test-0.5.0.dist-info/WHEEL
packaging_demo_py_to_prd_test-0.5.0.dist-info/top_level.txt
packaging_demo_py_to_prd_test-0.5.0.dist-info/RECORD
