Metadata-Version: 2.4
Name: packaging-demo-py-to-prd-test
Version: 0.5.0
Summary: My package description
Author-email: Josiah Carberry <josiah_carberry@brown.edu>
License-Expression: MIT
Keywords: one,two
Classifier: Programming Language :: Python :: 3
Requires-Python: >=3.8
Requires-Dist: numpy
Requires-Dist: importlib-metadata; python_version < "3.10"
Provides-Extra: test
Requires-Dist: pytest; extra == "test"
Requires-Dist: pytest-cov; extra == "test"
Provides-Extra: release
Requires-Dist: build; extra == "release"
Requires-Dist: twine; extra == "release"
Provides-Extra: static-code-qa
Requires-Dist: pre-commit; extra == "static-code-qa"
Provides-Extra: dev
Requires-Dist: packaging-demo[release,static-code-qa,test]; extra == "dev"
